ramantools/__init__.py
ramantools/ramantools.py
ramantools/version.py
ramantools-0.3.4.dist-info/LICENSE
ramantools-0.3.4.dist-info/METADATA
ramantools-0.3.4.dist-info/WHEEL
ramantools-0.3.4.dist-info/top_level.txt
ramantools-0.3.4.dist-info/RECORD
