Metadata-Version: 2.1
Name: ramantools
Version: 0.3.4
Summary: Tools for analyzing Raman spectroscopy data, measured by a Witec confocal Raman microscope.
Home-page: https://github.com/zrbyte/ramantools
Author: Peter Nemes-Incze
Classifier: License :: OSI Approved :: MIT License
Classifier: Programming Language :: Python :: 3
Classifier: Operating System :: OS Independent
License-File: LICENSE
Requires-Dist: matplotlib
Requires-Dist: numpy
Requires-Dist: pandas
Requires-Dist: scipy
Requires-Dist: xarray>=2023.7.0
